line/py/line.py
Nectrlline-1.dist-info/METADATA
Nectrlline-1.dist-info/WHEEL
Nectrlline-1.dist-info/top_level.txt
Nectrlline-1.dist-info/RECORD
