Metadata-Version: 2.1
Name: Nectrlline
Version: 1
Summary: Awesome library
Home-page: https://github.com/whatever/whatever
Author: amzon_0021
Author-email: riimuww@gmail.com
License: MIT
Keywords: sample setuptools development
Platform: UNKNOWN
Classifier: Programming Language :: Python :: 3.7
